setup.py
django_template_i18n_lint/__init__.py
django_template_i18n_lint/_version.py
django_template_i18n_lint.egg-info/PKG-INFO
django_template_i18n_lint.egg-info/SOURCES.txt
django_template_i18n_lint.egg-info/dependency_links.txt
django_template_i18n_lint.egg-info/entry_points.txt
django_template_i18n_lint.egg-info/top_level.txt