Metadata-Version: 1.1
Name: django-template-i18n-lint
Version: 1.2.1
Summary: Lint tool to find non-trans/blocktrans text in django templates
Home-page: http://www.technomancy.org/python/django-template-i18n-lint/
Author: Rory McCann
Author-email: rory@technomancy.org
License: GPLv3+
Platform: UNKNOWN
Classifier: Development Status :: 5 - Production/Stable
Classifier: License :: OSI Approved :: GNU General Public License v3 or later (GPLv3+)
Classifier: License :: OSI Approved :: BSD License
Classifier: Environment :: Console
Classifier: Framework :: Django
Classifier: Intended Audience :: Developers
Classifier: Operating System :: OS Independent
Classifier: Programming Language :: Python
Classifier: Programming Language :: Python :: 2
Classifier: Programming Language :: Python :: 2.7
Classifier: Programming Language :: Python :: 3
Classifier: Programming Language :: Python :: 3.3
